auth_token/__init__.py
auth_token/security.py
auth_token/utils.py
auth_token-0.0.3.dist-info/METADATA
auth_token-0.0.3.dist-info/WHEEL
auth_token-0.0.3.dist-info/top_level.txt
auth_token-0.0.3.dist-info/RECORD
