Metadata-Version: 2.1
Name: auth-token
Version: 0.0.3
Summary: Auth token jwt
Home-page: https://gitlab.com/developerjoseph/auth-token
Author: Jose Salas
Author-email: josephsalas.developer@gmail.com
License: UNKNOWN
Platform: UNKNOWN
Classifier: Programming Language :: Python :: 3
Classifier: License :: OSI Approved :: MIT License
Classifier: Operating System :: OS Independent
Requires-Python: >=3.6
